aioblackbird24180/__init__.py
aioblackbird24180/blackbird.py
aioblackbird24180/http.py
aioblackbird24180/util.py
aioblackbird24180-0.1.2.dist-info/LICENSE
aioblackbird24180-0.1.2.dist-info/METADATA
aioblackbird24180-0.1.2.dist-info/WHEEL
aioblackbird24180-0.1.2.dist-info/top_level.txt
aioblackbird24180-0.1.2.dist-info/RECORD
